[{"close": 0.4439, "high": 0.4443, "low": 0.4428, "open": 0.4428, "time": 1761364800, "volume": 183840}, {"close": 0.4424, "high": 0.4446, "low": 0.4424, "open": 0.4445, "time": 1761361200, "volume": 5342}, {"close": 0.4445, "high": 0.4457, "low": 0.4445, "open": 0.4457, "time": 1761357600, "volume": 154}, {"close": 0.4452, "high": 0.4467, "low": 0.4448, "open": 0.445, "time": 1761354000, "volume": 2095}, {"close": 0.4458, "high": 0.4467, "low": 0.4458, "open": 0.446, "time": 1761350400, "volume": 547}, {"close": 0.4481, "high": 0.4481, "low": 0.4481, "open": 0.4481, "time": 1761346800, "volume": 500}, {"close": 0.4477, "high": 0.4477, "low": 0.4477, "open": 0.4477, "time": 1761343200, "volume": 0}, {"close": 0.4477, "high": 0.4487, "low": 0.4476, "open": 0.4487, "time": 1761339600, "volume": 286}, {"close": 0.4449, "high": 0.4449, "low": 0.4449, "open": 0.4449, "time": 1761336000, "volume": 0}, {"close": 0.4449, "high": 0.445, "low": 0.443, "open": 0.443, "time": 1761332400, "volume": 3119}, {"close": 0.4392, "high": 0.4392, "low": 0.4385, "open": 0.4385, "time": 1761328800, "volume": 248}, {"close": 0.4363, "high": 0.4375, "low": 0.4354, "open": 0.4374, "time": 1761325200, "volume": 6119}, {"close": 0.4347, "high": 0.4369, "low": 0.4336, "open": 0.4336, "time": 1761321600, "volume": 127475}, {"close": 0.4397, "high": 0.4397, "low": 0.4392, "open": 0.4392, "time": 1761318000, "volume": 245}, {"close": 0.4377, "high": 0.4383, "low": 0.4351, "open": 0.4383, "time": 1761314400, "volume": 13095}, {"close": 0.4424, "high": 0.4452, "low": 0.4397, "open": 0.444, "time": 1761310800, "volume": 184334}, {"close": 0.4477, "high": 0.4511, "low": 0.4418, "open": 0.4418, "time": 1761307200, "volume": 21530}, {"close": 0.4404, "high": 0.4404, "low": 0.4375, "open": 0.4386, "time": 1761303600, "volume": 3487}, {"close": 0.4405, "high": 0.4407, "low": 0.4396, "open": 0.4401, "time": 1761300000, "volume": 3488}, {"close": 0.4407, "high": 0.4434, "low": 0.4407, "open": 0.4434, "time": 1761296400, "volume": 4875}, {"close": 0.445, "high": 0.445, "low": 0.4388, "open": 0.4401, "time": 1761292800, "volume": 4666}, {"close": 0.4395, "high": 0.4424, "low": 0.4382, "open": 0.4424, "time": 1761289200, "volume": 5807}, {"close": 0.4435, "high": 0.4435, "low": 0.441, "open": 0.4423, "time": 1761285600, "volume": 6217}, {"close": 0.4431, "high": 0.4431, "low": 0.4394, "open": 0.4404, "time": 1761282000, "volume": 14034}, {"close": 0.4398, "high": 0.4407, "low": 0.4306, "open": 0.4306, "time": 1761278400, "volume": 16428}, {"close": 0.4311, "high": 0.4323, "low": 0.4306, "open": 0.4323, "time": 1761274800, "volume": 8327}, {"close": 0.4322, "high": 0.4338, "low": 0.4322, "open": 0.4335, "time": 1761271200, "volume": 232474}, {"close": 0.433, "high": 0.4339, "low": 0.433, "open": 0.4339, "time": 1761267600, "volume": 27}, {"close": 0.433, "high": 0.433, "low": 0.433, "open": 0.433, "time": 1761264000, "volume": 86}, {"close": 0.4319, "high": 0.4319, "low": 0.4319, "open": 0.4319, "time": 1761260400, "volume": 6000}, {"close": 0.4318, "high": 0.4318, "low": 0.4318, "open": 0.4318, "time": 1761256800, "volume": 1000}, {"close": 0.4292, "high": 0.4293, "low": 0.4287, "open": 0.4293, "time": 1761253200, "volume": 220102}, {"close": 0.4303, "high": 0.434, "low": 0.4303, "open": 0.434, "time": 1761249600, "volume": 7250}, {"close": 0.4342, "high": 0.4342, "low": 0.432, "open": 0.4331, "time": 1761246000, "volume": 3709}, {"close": 0.434, "high": 0.438, "low": 0.434, "open": 0.438, "time": 1761242400, "volume": 18921}, {"close": 0.439, "high": 0.4393, "low": 0.4346, "open": 0.4364, "time": 1761238800, "volume": 20677}, {"close": 0.4366, "high": 0.4366, "low": 0.4323, "open": 0.4336, "time": 1761235200, "volume": 240776}, {"close": 0.4323, "high": 0.4336, "low": 0.4287, "open": 0.4287, "time": 1761231600, "volume": 13501}, {"close": 0.4291, "high": 0.4304, "low": 0.4287, "open": 0.429, "time": 1761228000, "volume": 3533}, {"close": 0.4316, "high": 0.4316, "low": 0.4274, "open": 0.4274, "time": 1761224400, "volume": 6285}, {"close": 0.4281, "high": 0.4281, "low": 0.4265, "open": 0.4265, "time": 1761220800, "volume": 3297}, {"close": 0.4286, "high": 0.4307, "low": 0.4285, "open": 0.4292, "time": 1761217200, "volume": 56}, {"close": 0.4303, "high": 0.4341, "low": 0.4302, "open": 0.4323, "time": 1761213600, "volume": 13647}, {"close": 0.4296, "high": 0.43, "low": 0.4294, "open": 0.4294, "time": 1761210000, "volume": 224507}, {"close": 0.4306, "high": 0.431, "low": 0.4289, "open": 0.4289, "time": 1761206400, "volume": 3621}, {"close": 0.4283, "high": 0.4287, "low": 0.4279, "open": 0.4283, "time": 1761202800, "volume": 5658}, {"close": 0.4292, "high": 0.4298, "low": 0.4224, "open": 0.4224, "time": 1761199200, "volume": 21043}, {"close": 0.4221, "high": 0.4221, "low": 0.4214, "open": 0.4214, "time": 1761195600, "volume": 1242}, {"close": 0.4223, "high": 0.4239, "low": 0.4205, "open": 0.4214, "time": 1761192000, "volume": 3329}, {"close": 0.4208, "high": 0.4222, "low": 0.4202, "open": 0.4203, "time": 1761188400, "volume": 242221}, {"close": 0.4198, "high": 0.4208, "low": 0.4194, "open": 0.4194, "time": 1761184800, "volume": 2396}, {"close": 0.4198, "high": 0.4204, "low": 0.4197, "open": 0.4197, "time": 1761181200, "volume": 3193}, {"close": 0.4205, "high": 0.4205, "low": 0.4183, "open": 0.4183, "time": 1761177600, "volume": 1176}, {"close": 0.4165, "high": 0.4165, "low": 0.4137, "open": 0.4137, "time": 1761174000, "volume": 8550}, {"close": 0.4118, "high": 0.4118, "low": 0.4118, "open": 0.4118, "time": 1761170400, "volume": 0}, {"close": 0.4118, "high": 0.4151, "low": 0.405, "open": 0.4151, "time": 1761166800, "volume": 237525}, {"close": 0.4197, "high": 0.4197, "low": 0.4197, "open": 0.4197, "time": 1761163200, "volume": 1147}, {"close": 0.4196, "high": 0.4196, "low": 0.4186, "open": 0.4186, "time": 1761159600, "volume": 2304}, {"close": 0.4224, "high": 0.4259, "low": 0.4214, "open": 0.4259, "time": 1761156000, "volume": 11293}, {"close": 0.4227, "high": 0.4294, "low": 0.4227, "open": 0.4294, "time": 1761152400, "volume": 10652}, {"close": 0.4312, "high": 0.4327, "low": 0.4289, "open": 0.4301, "time": 1761148800, "volume": 1172}, {"close": 0.4327, "high": 0.4363, "low": 0.4286, "open": 0.4363, "time": 1761145200, "volume": 1170}, {"close": 0.4265, "high": 0.4369, "low": 0.4265, "open": 0.4355, "time": 1761141600, "volume": 237096}, {"close": 0.4358, "high": 0.4358, "low": 0.4299, "open": 0.4302, "time": 1761138000, "volume": 15345}, {"close": 0.4309, "high": 0.4348, "low": 0.4303, "open": 0.4313, "time": 1761134400, "volume": 9989}, {"close": 0.4318, "high": 0.4346, "low": 0.424, "open": 0.4264, "time": 1761130800, "volume": 5279}, {"close": 0.4272, "high": 0.4298, "low": 0.4272, "open": 0.4288, "time": 1761127200, "volume": 4864}, {"close": 0.4288, "high": 0.4306, "low": 0.4288, "open": 0.4306, "time": 1761123600, "volume": 2586}, {"close": 0.4301, "high": 0.4324, "low": 0.4297, "open": 0.4297, "time": 1761120000, "volume": 147}, {"close": 0.4312, "high": 0.4314, "low": 0.4284, "open": 0.4289, "time": 1761116400, "volume": 13012}, {"close": 0.4308, "high": 0.4318, "low": 0.4304, "open": 0.4309, "time": 1761112800, "volume": 5531}, {"close": 0.4324, "high": 0.4335, "low": 0.429, "open": 0.4335, "time": 1761109200, "volume": 21109}, {"close": 0.4369, "high": 0.4376, "low": 0.4356, "open": 0.4376, "time": 1761105600, "volume": 11194}, {"close": 0.4322, "high": 0.4325, "low": 0.431, "open": 0.4319, "time": 1761102000, "volume": 1493}, {"close": 0.4336, "high": 0.4352, "low": 0.4335, "open": 0.4336, "time": 1761098400, "volume": 2335}, {"close": 0.4313, "high": 0.4339, "low": 0.4307, "open": 0.4339, "time": 1761094800, "volume": 18998}, {"close": 0.4315, "high": 0.4346, "low": 0.4315, "open": 0.4346, "time": 1761091200, "volume": 134}, {"close": 0.4399, "high": 0.4399, "low": 0.4399, "open": 0.4399, "time": 1761087600, "volume": 0}, {"close": 0.4399, "high": 0.44, "low": 0.4399, "open": 0.44, "time": 1761084000, "volume": 5112}, {"close": 0.4489, "high": 0.4528, "low": 0.4489, "open": 0.4528, "time": 1761080400, "volume": 1451}, {"close": 0.4526, "high": 0.4551, "low": 0.4518, "open": 0.4551, "time": 1761076800, "volume": 110283}, {"close": 0.4572, "high": 0.4584, "low": 0.4568, "open": 0.4582, "time": 1761073200, "volume": 1060}, {"close": 0.4583, "high": 0.4607, "low": 0.4583, "open": 0.4605, "time": 1761069600, "volume": 2089}, {"close": 0.454, "high": 0.4582, "low": 0.4534, "open": 0.4575, "time": 1761066000, "volume": 2369}, {"close": 0.456, "high": 0.4649, "low": 0.456, "open": 0.4634, "time": 1761062400, "volume": 23616}, {"close": 0.4609, "high": 0.4667, "low": 0.4559, "open": 0.4582, "time": 1761058800, "volume": 22254}, {"close": 0.4575, "high": 0.4575, "low": 0.4387, "open": 0.4387, "time": 1761055200, "volume": 50968}, {"close": 0.4368, "high": 0.4417, "low": 0.4368, "open": 0.4392, "time": 1761051600, "volume": 4508}, {"close": 0.438, "high": 0.4416, "low": 0.4337, "open": 0.4349, "time": 1761048000, "volume": 17619}, {"close": 0.4353, "high": 0.4367, "low": 0.4335, "open": 0.4363, "time": 1761044400, "volume": 162762}, {"close": 0.4367, "high": 0.4367, "low": 0.4325, "open": 0.4325, "time": 1761040800, "volume": 5013}, {"close": 0.428, "high": 0.428, "low": 0.428, "open": 0.428, "time": 1761037200, "volume": 0}, {"close": 0.428, "high": 0.4314, "low": 0.428, "open": 0.4314, "time": 1761033600, "volume": 312}, {"close": 0.4329, "high": 0.4329, "low": 0.4314, "open": 0.4314, "time": 1761030000, "volume": 15224}, {"close": 0.4282, "high": 0.4282, "low": 0.4282, "open": 0.4282, "time": 1761026400, "volume": 0}, {"close": 0.4282, "high": 0.4291, "low": 0.4268, "open": 0.4268, "time": 1761022800, "volume": 3990}, {"close": 0.4266, "high": 0.4335, "low": 0.4266, "open": 0.4335, "time": 1761019200, "volume": 9098}, {"close": 0.4362, "high": 0.4389, "low": 0.4362, "open": 0.4389, "time": 1761015600, "volume": 5581}, {"close": 0.4389, "high": 0.4418, "low": 0.4373, "open": 0.4418, "time": 1761012000, "volume": 21408}, {"close": 0.442, "high": 0.4437, "low": 0.442, "open": 0.4437, "time": 1761008400, "volume": 535}, {"close": 0.448, "high": 0.448, "low": 0.448, "open": 0.448, "time": 1761004800, "volume": 0}, {"close": 0.448, "high": 0.448, "low": 0.4477, "open": 0.4477, "time": 1761001200, "volume": 1786}, {"close": 0.4487, "high": 0.4487, "low": 0.4487, "open": 0.4487, "time": 1760997600, "volume": 2500}, {"close": 0.449, "high": 0.449, "low": 0.449, "open": 0.449, "time": 1760994000, "volume": 2500}, {"close": 0.4494, "high": 0.4496, "low": 0.4494, "open": 0.4496, "time": 1760990400, "volume": 2511}, {"close": 0.4462, "high": 0.4462, "low": 0.4462, "open": 0.4462, "time": 1760986800, "volume": 0}, {"close": 0.4462, "high": 0.4462, "low": 0.4462, "open": 0.4462, "time": 1760983200, "volume": 2473}, {"close": 0.4436, "high": 0.4465, "low": 0.4421, "open": 0.4465, "time": 1760979600, "volume": 105618}, {"close": 0.4453, "high": 0.4472, "low": 0.4402, "open": 0.4465, "time": 1760976000, "volume": 8946}, {"close": 0.4507, "high": 0.4551, "low": 0.4507, "open": 0.4551, "time": 1760972400, "volume": 70336}, {"close": 0.4551, "high": 0.4568, "low": 0.452, "open": 0.4548, "time": 1760968800, "volume": 79064}, {"close": 0.4545, "high": 0.455, "low": 0.4501, "open": 0.4503, "time": 1760965200, "volume": 28070}, {"close": 0.449, "high": 0.4495, "low": 0.449, "open": 0.4495, "time": 1760961600, "volume": 2526}, {"close": 0.4494, "high": 0.4507, "low": 0.4479, "open": 0.45, "time": 1760958000, "volume": 3178}, {"close": 0.4478, "high": 0.4525, "low": 0.4477, "open": 0.4495, "time": 1760954400, "volume": 1835}, {"close": 0.4498, "high": 0.4498, "low": 0.4492, "open": 0.4494, "time": 1760950800, "volume": 5647}, {"close": 0.4472, "high": 0.4488, "low": 0.4455, "open": 0.4481, "time": 1760947200, "volume": 57275}, {"close": 0.4486, "high": 0.453, "low": 0.4472, "open": 0.453, "time": 1760943600, "volume": 18552}, {"close": 0.4543, "high": 0.4557, "low": 0.4502, "open": 0.4504, "time": 1760940000, "volume": 16882}, {"close": 0.4499, "high": 0.4499, "low": 0.4481, "open": 0.4481, "time": 1760936400, "volume": 3236}, {"close": 0.4485, "high": 0.4502, "low": 0.4476, "open": 0.4502, "time": 1760932800, "volume": 26395}, {"close": 0.4484, "high": 0.4506, "low": 0.4385, "open": 0.439, "time": 1760929200, "volume": 4713}, {"close": 0.4376, "high": 0.4377, "low": 0.4335, "open": 0.4342, "time": 1760925600, "volume": 136859}, {"close": 0.4359, "high": 0.4378, "low": 0.4352, "open": 0.4376, "time": 1760922000, "volume": 45018}, {"close": 0.4365, "high": 0.4376, "low": 0.4307, "open": 0.4376, "time": 1760918400, "volume": 50356}, {"close": 0.438, "high": 0.438, "low": 0.438, "open": 0.438, "time": 1760914800, "volume": 119178}, {"close": 0.4392, "high": 0.4392, "low": 0.4392, "open": 0.4392, "time": 1760911200, "volume": 0}, {"close": 0.4392, "high": 0.4395, "low": 0.4392, "open": 0.4395, "time": 1760907600, "volume": 1385}, {"close": 0.4411, "high": 0.4411, "low": 0.4411, "open": 0.4411, "time": 1760904000, "volume": 0}, {"close": 0.4411, "high": 0.4411, "low": 0.4405, "open": 0.4405, "time": 1760900400, "volume": 1423}, {"close": 0.4409, "high": 0.4409, "low": 0.4389, "open": 0.4393, "time": 1760896800, "volume": 27281}, {"close": 0.4387, "high": 0.445, "low": 0.4387, "open": 0.4395, "time": 1760893200, "volume": 79188}, {"close": 0.44, "high": 0.4413, "low": 0.4374, "open": 0.4375, "time": 1760889600, "volume": 4214}, {"close": 0.4387, "high": 0.4392, "low": 0.4368, "open": 0.4386, "time": 1760886000, "volume": 3023}, {"close": 0.4404, "high": 0.4411, "low": 0.438, "open": 0.4381, "time": 1760882400, "volume": 42649}, {"close": 0.4386, "high": 0.4392, "low": 0.432, "open": 0.4325, "time": 1760878800, "volume": 36890}, {"close": 0.4315, "high": 0.4343, "low": 0.4313, "open": 0.4343, "time": 1760875200, "volume": 11921}, {"close": 0.4351, "high": 0.4389, "low": 0.4351, "open": 0.4369, "time": 1760871600, "volume": 14045}, {"close": 0.4341, "high": 0.4366, "low": 0.4303, "open": 0.4305, "time": 1760868000, "volume": 123796}, {"close": 0.4306, "high": 0.434, "low": 0.4223, "open": 0.4225, "time": 1760864400, "volume": 9341}, {"close": 0.424, "high": 0.4319, "low": 0.4228, "open": 0.4283, "time": 1760860800, "volume": 10200}, {"close": 0.4251, "high": 0.4276, "low": 0.4251, "open": 0.4273, "time": 1760857200, "volume": 107968}, {"close": 0.425, "high": 0.4254, "low": 0.424, "open": 0.4253, "time": 1760853600, "volume": 63238}, {"close": 0.4297, "high": 0.4297, "low": 0.4277, "open": 0.4277, "time": 1760850000, "volume": 145}, {"close": 0.4275, "high": 0.4322, "low": 0.4267, "open": 0.4318, "time": 1760846400, "volume": 2950}, {"close": 0.4299, "high": 0.4318, "low": 0.4265, "open": 0.4265, "time": 1760842800, "volume": 2366}, {"close": 0.4249, "high": 0.4273, "low": 0.4249, "open": 0.4269, "time": 1760839200, "volume": 958}, {"close": 0.4265, "high": 0.4265, "low": 0.4255, "open": 0.4255, "time": 1760835600, "volume": 43000}, {"close": 0.425, "high": 0.425, "low": 0.4244, "open": 0.4244, "time": 1760832000, "volume": 4259}, {"close": 0.426, "high": 0.426, "low": 0.426, "open": 0.426, "time": 1760828400, "volume": 0}, {"close": 0.426, "high": 0.426, "low": 0.426, "open": 0.426, "time": 1760824800, "volume": 0}, {"close": 0.426, "high": 0.426, "low": 0.426, "open": 0.426, "time": 1760821200, "volume": 31}, {"close": 0.4256, "high": 0.4256, "low": 0.4256, "open": 0.4256, "time": 1760817600, "volume": 0}, {"close": 0.4256, "high": 0.4256, "low": 0.4245, "open": 0.4245, "time": 1760814000, "volume": 44857}, {"close": 0.4239, "high": 0.4253, "low": 0.4239, "open": 0.4251, "time": 1760810400, "volume": 3995}, {"close": 0.4198, "high": 0.4205, "low": 0.4198, "open": 0.4205, "time": 1760806800, "volume": 220}, {"close": 0.4206, "high": 0.4215, "low": 0.419, "open": 0.4215, "time": 1760803200, "volume": 3597}, {"close": 0.4227, "high": 0.4227, "low": 0.4227, "open": 0.4227, "time": 1760799600, "volume": 0}, {"close": 0.4227, "high": 0.4227, "low": 0.4227, "open": 0.4227, "time": 1760796000, "volume": 0}, {"close": 0.4227, "high": 0.4246, "low": 0.4227, "open": 0.4246, "time": 1760792400, "volume": 481}, {"close": 0.4276, "high": 0.4281, "low": 0.4275, "open": 0.4281, "time": 1760788800, "volume": 12}, {"close": 0.4273, "high": 0.4273, "low": 0.427, "open": 0.427, "time": 1760785200, "volume": 81}, {"close": 0.4257, "high": 0.4257, "low": 0.4257, "open": 0.4257, "time": 1760781600, "volume": 9}, {"close": 0.4254, "high": 0.4254, "low": 0.4209, "open": 0.4209, "time": 1760778000, "volume": 950}, {"close": 0.4232, "high": 0.424, "low": 0.4222, "open": 0.423, "time": 1760774400, "volume": 4166}, {"close": 0.4217, "high": 0.4293, "low": 0.4217, "open": 0.4235, "time": 1760770800, "volume": 4571}, {"close": 0.4223, "high": 0.4223, "low": 0.4223, "open": 0.4223, "time": 1760767200, "volume": 80}, {"close": 0.4184, "high": 0.4204, "low": 0.4184, "open": 0.4204, "time": 1760763600, "volume": 182}, {"close": 0.3994, "high": 0.4015, "low": 0.399, "open": 0.4015, "time": 1761969600, "volume": 9575}, {"close": 0.4018, "high": 0.4018, "low": 0.4015, "open": 0.4016, "time": 1761966000, "volume": 365}, {"close": 0.397, "high": 0.397, "low": 0.397, "open": 0.397, "time": 1761962400, "volume": 500}, {"close": 0.3976, "high": 0.4014, "low": 0.3976, "open": 0.4014, "time": 1761958800, "volume": 5058}, {"close": 0.3988, "high": 0.3988, "low": 0.3988, "open": 0.3988, "time": 1761955200, "volume": 0}, {"close": 0.3988, "high": 0.3988, "low": 0.3988, "open": 0.3988, "time": 1761951600, "volume": 4217}, {"close": 0.3975, "high": 0.3975, "low": 0.3975, "open": 0.3975, "time": 1761948000, "volume": 600}, {"close": 0.399, "high": 0.399, "low": 0.399, "open": 0.399, "time": 1761944400, "volume": 0}, {"close": 0.399, "high": 0.4008, "low": 0.399, "open": 0.4008, "time": 1761940800, "volume": 600}, {"close": 0.4036, "high": 0.4038, "low": 0.392, "open": 0.392, "time": 1761937200, "volume": 118427}, {"close": 0.3927, "high": 0.3959, "low": 0.3907, "open": 0.3934, "time": 1761933600, "volume": 105726}, {"close": 0.3917, "high": 0.3935, "low": 0.3874, "open": 0.3909, "time": 1761930000, "volume": 20353}, {"close": 0.3919, "high": 0.4037, "low": 0.3919, "open": 0.4037, "time": 1761926400, "volume": 9921}, {"close": 0.4051, "high": 0.4059, "low": 0.4028, "open": 0.4028, "time": 1761922800, "volume": 3770}, {"close": 0.4039, "high": 0.4039, "low": 0.3982, "open": 0.4004, "time": 1761919200, "volume": 5773}, {"close": 0.4024, "high": 0.4044, "low": 0.398, "open": 0.4031, "time": 1761915600, "volume": 49380}, {"close": 0.4022, "high": 0.4075, "low": 0.4022, "open": 0.4053, "time": 1761912000, "volume": 21917}, {"close": 0.4045, "high": 0.4047, "low": 0.399, "open": 0.3998, "time": 1761908400, "volume": 33967}, {"close": 0.4012, "high": 0.4012, "low": 0.3987, "open": 0.3987, "time": 1761904800, "volume": 1279}, {"close": 0.4001, "high": 0.4001, "low": 0.3975, "open": 0.3978, "time": 1761901200, "volume": 8337}, {"close": 0.3985, "high": 0.3997, "low": 0.3965, "open": 0.3997, "time": 1761897600, "volume": 67469}, {"close": 0.3979, "high": 0.4001, "low": 0.3979, "open": 0.3986, "time": 1761894000, "volume": 29493}, {"close": 0.3979, "high": 0.3983, "low": 0.3979, "open": 0.3983, "time": 1761890400, "volume": 111}, {"close": 0.4013, "high": 0.4032, "low": 0.4013, "open": 0.4031, "time": 1761886800, "volume": 1009}, {"close": 0.4041, "high": 0.4041, "low": 0.4013, "open": 0.4034, "time": 1761883200, "volume": 540}, {"close": 0.3995, "high": 0.4037, "low": 0.3995, "open": 0.4037, "time": 1761879600, "volume": 1397}, {"close": 0.4033, "high": 0.4057, "low": 0.4033, "open": 0.4057, "time": 1761876000, "volume": 1718}, {"close": 0.4074, "high": 0.4078, "low": 0.4056, "open": 0.4056, "time": 1761872400, "volume": 3306}, {"close": 0.4004, "high": 0.402, "low": 0.4004, "open": 0.4008, "time": 1761868800, "volume": 539}, {"close": 0.399, "high": 0.399, "low": 0.3977, "open": 0.3977, "time": 1761865200, "volume": 156}, {"close": 0.3915, "high": 0.3915, "low": 0.3915, "open": 0.3915, "time": 1761861600, "volume": 0}, {"close": 0.3915, "high": 0.3915, "low": 0.3913, "open": 0.3913, "time": 1761858000, "volume": 2890}, {"close": 0.3927, "high": 0.3931, "low": 0.3887, "open": 0.3888, "time": 1761854400, "volume": 670}, {"close": 0.3884, "high": 0.391, "low": 0.3878, "open": 0.391, "time": 1761850800, "volume": 5227}, {"close": 0.3914, "high": 0.3941, "low": 0.3914, "open": 0.3941, "time": 1761847200, "volume": 540}, {"close": 0.3944, "high": 0.3969, "low": 0.3898, "open": 0.3969, "time": 1761843600, "volume": 23051}, {"close": 0.3985, "high": 0.403, "low": 0.3978, "open": 0.4022, "time": 1761840000, "volume": 3400}, {"close": 0.4005, "high": 0.4058, "low": 0.3998, "open": 0.4058, "time": 1761836400, "volume": 10383}, {"close": 0.409, "high": 0.4102, "low": 0.4062, "open": 0.4072, "time": 1761832800, "volume": 17601}, {"close": 0.412, "high": 0.4173, "low": 0.4087, "open": 0.4154, "time": 1761829200, "volume": 95743}, {"close": 0.4152, "high": 0.4222, "low": 0.4152, "open": 0.4222, "time": 1761825600, "volume": 3357}, {"close": 0.4262, "high": 0.4262, "low": 0.4262, "open": 0.4262, "time": 1761822000, "volume": 2}, {"close": 0.4249, "high": 0.429, "low": 0.4249, "open": 0.4276, "time": 1761818400, "volume": 5765}, {"close": 0.4285, "high": 0.4317, "low": 0.4275, "open": 0.4317, "time": 1761814800, "volume": 18143}, {"close": 0.4319, "high": 0.4374, "low": 0.4319, "open": 0.4374, "time": 1761811200, "volume": 414}, {"close": 0.438, "high": 0.438, "low": 0.4371, "open": 0.4371, "time": 1761807600, "volume": 3000}, {"close": 0.4349, "high": 0.4349, "low": 0.4312, "open": 0.4335, "time": 1761804000, "volume": 113}, {"close": 0.435, "high": 0.4353, "low": 0.4257, "open": 0.4268, "time": 1761800400, "volume": 23201}, {"close": 0.4304, "high": 0.4418, "low": 0.423, "open": 0.4418, "time": 1761796800, "volume": 12674}, {"close": 0.4412, "high": 0.4452, "low": 0.4404, "open": 0.4452, "time": 1761793200, "volume": 728}, {"close": 0.4451, "high": 0.4468, "low": 0.4419, "open": 0.4419, "time": 1761789600, "volume": 5288}, {"close": 0.4411, "high": 0.4424, "low": 0.4402, "open": 0.4424, "time": 1761786000, "volume": 244}, {"close": 0.4446, "high": 0.4447, "low": 0.4368, "open": 0.4396, "time": 1761782400, "volume": 11115}, {"close": 0.4404, "high": 0.4448, "low": 0.4388, "open": 0.4448, "time": 1761778800, "volume": 8193}, {"close": 0.4503, "high": 0.4506, "low": 0.4497, "open": 0.4501, "time": 1761775200, "volume": 6720}, {"close": 0.4532, "high": 0.4532, "low": 0.4532, "open": 0.4532, "time": 1761771600, "volume": 0}, {"close": 0.4532, "high": 0.4532, "low": 0.4459, "open": 0.4475, "time": 1761768000, "volume": 74}, {"close": 0.4439, "high": 0.448, "low": 0.4416, "open": 0.4416, "time": 1761764400, "volume": 6030}, {"close": 0.4395, "high": 0.4508, "low": 0.427, "open": 0.4508, "time": 1761760800, "volume": 47687}, {"close": 0.4469, "high": 0.4477, "low": 0.4387, "open": 0.4399, "time": 1761757200, "volume": 23254}, {"close": 0.4382, "high": 0.4426, "low": 0.4376, "open": 0.4385, "time": 1761753600, "volume": 7475}, {"close": 0.4391, "high": 0.4458, "low": 0.4378, "open": 0.4458, "time": 1761750000, "volume": 44206}, {"close": 0.4447, "high": 0.4459, "low": 0.4431, "open": 0.4459, "time": 1761746400, "volume": 13021}, {"close": 0.4473, "high": 0.4487, "low": 0.447, "open": 0.4487, "time": 1761742800, "volume": 10480}, {"close": 0.4457, "high": 0.4464, "low": 0.4452, "open": 0.4452, "time": 1761739200, "volume": 1946}, {"close": 0.4451, "high": 0.4467, "low": 0.4451, "open": 0.4461, "time": 1761735600, "volume": 6056}, {"close": 0.4432, "high": 0.4434, "low": 0.4385, "open": 0.4393, "time": 1761732000, "volume": 26732}, {"close": 0.4376, "high": 0.4376, "low": 0.4342, "open": 0.4357, "time": 1761728400, "volume": 91555}, {"close": 0.4352, "high": 0.4357, "low": 0.4345, "open": 0.4357, "time": 1761724800, "volume": 403}, {"close": 0.4377, "high": 0.4387, "low": 0.4347, "open": 0.438, "time": 1761721200, "volume": 4801}, {"close": 0.4353, "high": 0.4361, "low": 0.4353, "open": 0.4361, "time": 1761717600, "volume": 2700}, {"close": 0.436, "high": 0.4369, "low": 0.436, "open": 0.4361, "time": 1761714000, "volume": 14372}, {"close": 0.4353, "high": 0.4353, "low": 0.4353, "open": 0.4353, "time": 1761710400, "volume": 4}, {"close": 0.4347, "high": 0.4347, "low": 0.4345, "open": 0.4345, "time": 1761706800, "volume": 54}, {"close": 0.4358, "high": 0.4367, "low": 0.4353, "open": 0.436, "time": 1761703200, "volume": 7028}, {"close": 0.436, "high": 0.436, "low": 0.4337, "open": 0.4351, "time": 1761699600, "volume": 2259}, {"close": 0.4346, "high": 0.4355, "low": 0.4346, "open": 0.4348, "time": 1761696000, "volume": 2430}, {"close": 0.4359, "high": 0.4359, "low": 0.4351, "open": 0.4351, "time": 1761692400, "volume": 9}, {"close": 0.4367, "high": 0.4367, "low": 0.4322, "open": 0.4322, "time": 1761688800, "volume": 3075}, {"close": 0.4331, "high": 0.4331, "low": 0.4293, "open": 0.4293, "time": 1761685200, "volume": 250}, {"close": 0.4334, "high": 0.4402, "low": 0.4305, "open": 0.4402, "time": 1761681600, "volume": 1290}, {"close": 0.4422, "high": 0.4485, "low": 0.44, "open": 0.4485, "time": 1761678000, "volume": 917}, {"close": 0.4495, "high": 0.4537, "low": 0.4495, "open": 0.453, "time": 1761674400, "volume": 13434}, {"close": 0.455, "high": 0.4558, "low": 0.4541, "open": 0.4558, "time": 1761670800, "volume": 3457}, {"close": 0.4561, "high": 0.4566, "low": 0.45, "open": 0.4514, "time": 1761667200, "volume": 15739}, {"close": 0.4514, "high": 0.4552, "low": 0.4504, "open": 0.4552, "time": 1761663600, "volume": 1375}, {"close": 0.4549, "high": 0.4598, "low": 0.4465, "open": 0.4593, "time": 1761660000, "volume": 3352}, {"close": 0.4595, "high": 0.4607, "low": 0.4583, "open": 0.4583, "time": 1761656400, "volume": 5359}, {"close": 0.4568, "high": 0.4576, "low": 0.4527, "open": 0.4527, "time": 1761652800, "volume": 144}, {"close": 0.4553, "high": 0.4553, "low": 0.4553, "open": 0.4553, "time": 1761649200, "volume": 10}, {"close": 0.4524, "high": 0.4543, "low": 0.4524, "open": 0.4531, "time": 1761645600, "volume": 908}, {"close": 0.4555, "high": 0.457, "low": 0.4555, "open": 0.457, "time": 1761642000, "volume": 14825}, {"close": 0.4535, "high": 0.4535, "low": 0.4535, "open": 0.4535, "time": 1761638400, "volume": 0}, {"close": 0.4535, "high": 0.4606, "low": 0.4535, "open": 0.4606, "time": 1761634800, "volume": 28961}, {"close": 0.4582, "high": 0.4582, "low": 0.449, "open": 0.4493, "time": 1761631200, "volume": 40119}, {"close": 0.4486, "high": 0.4548, "low": 0.4486, "open": 0.4548, "time": 1761627600, "volume": 44730}, {"close": 0.4539, "high": 0.4539, "low": 0.4519, "open": 0.4519, "time": 1761624000, "volume": 128}, {"close": 0.4511, "high": 0.4514, "low": 0.4498, "open": 0.4514, "time": 1761620400, "volume": 2308}, {"close": 0.4513, "high": 0.4533, "low": 0.4492, "open": 0.4533, "time": 1761616800, "volume": 2860}, {"close": 0.4531, "high": 0.4539, "low": 0.453, "open": 0.453, "time": 1761613200, "volume": 199}, {"close": 0.4533, "high": 0.4533, "low": 0.4533, "open": 0.4533, "time": 1761609600, "volume": 5000}, {"close": 0.451, "high": 0.451, "low": 0.4479, "open": 0.4482, "time": 1761606000, "volume": 5371}, {"close": 0.4507, "high": 0.4558, "low": 0.4507, "open": 0.4558, "time": 1761602400, "volume": 3005}, {"close": 0.4556, "high": 0.4556, "low": 0.4556, "open": 0.4556, "time": 1761598800, "volume": 0}, {"close": 0.4556, "high": 0.457, "low": 0.4546, "open": 0.457, "time": 1761595200, "volume": 2319}, {"close": 0.4587, "high": 0.4632, "low": 0.4585, "open": 0.4632, "time": 1761591600, "volume": 10563}, {"close": 0.4636, "high": 0.4674, "low": 0.4636, "open": 0.4658, "time": 1761588000, "volume": 15893}, {"close": 0.466, "high": 0.4678, "low": 0.4638, "open": 0.4639, "time": 1761584400, "volume": 4180}, {"close": 0.464, "high": 0.464, "low": 0.4589, "open": 0.46, "time": 1761580800, "volume": 6056}, {"close": 0.4577, "high": 0.4584, "low": 0.4566, "open": 0.4584, "time": 1761577200, "volume": 6918}, {"close": 0.4554, "high": 0.4557, "low": 0.4539, "open": 0.4554, "time": 1761573600, "volume": 267}, {"close": 0.4584, "high": 0.4591, "low": 0.4519, "open": 0.4573, "time": 1761570000, "volume": 14462}, {"close": 0.4554, "high": 0.4598, "low": 0.4554, "open": 0.4598, "time": 1761566400, "volume": 26216}, {"close": 0.4596, "high": 0.4597, "low": 0.4564, "open": 0.4597, "time": 1761562800, "volume": 9027}, {"close": 0.4585, "high": 0.4603, "low": 0.4584, "open": 0.4598, "time": 1761559200, "volume": 12672}, {"close": 0.4602, "high": 0.4623, "low": 0.4588, "open": 0.4623, "time": 1761555600, "volume": 25791}, {"close": 0.4649, "high": 0.4688, "low": 0.4649, "open": 0.4667, "time": 1761552000, "volume": 36108}, {"close": 0.4684, "high": 0.472, "low": 0.4649, "open": 0.4696, "time": 1761548400, "volume": 67005}, {"close": 0.472, "high": 0.4722, "low": 0.4702, "open": 0.4703, "time": 1761544800, "volume": 115858}, {"close": 0.473, "high": 0.4737, "low": 0.4722, "open": 0.4722, "time": 1761541200, "volume": 392}, {"close": 0.4703, "high": 0.4707, "low": 0.4678, "open": 0.4687, "time": 1761537600, "volume": 30532}, {"close": 0.4674, "high": 0.4701, "low": 0.4674, "open": 0.4696, "time": 1761534000, "volume": 8566}, {"close": 0.469, "high": 0.47, "low": 0.4668, "open": 0.4688, "time": 1761530400, "volume": 3270}, {"close": 0.47, "high": 0.47, "low": 0.4658, "open": 0.4658, "time": 1761526800, "volume": 31900}, {"close": 0.4659, "high": 0.4659, "low": 0.4647, "open": 0.4647, "time": 1761523200, "volume": 4393}, {"close": 0.4642, "high": 0.4665, "low": 0.4642, "open": 0.4664, "time": 1761519600, "volume": 12242}, {"close": 0.4648, "high": 0.4685, "low": 0.4648, "open": 0.4666, "time": 1761516000, "volume": 244842}, {"close": 0.4561, "high": 0.4561, "low": 0.4561, "open": 0.4561, "time": 1761512400, "volume": 86}, {"close": 0.4585, "high": 0.4609, "low": 0.4567, "open": 0.4609, "time": 1761508800, "volume": 17988}, {"close": 0.4615, "high": 0.4615, "low": 0.4602, "open": 0.4611, "time": 1761505200, "volume": 33050}, {"close": 0.4617, "high": 0.4617, "low": 0.461, "open": 0.4615, "time": 1761501600, "volume": 11137}, {"close": 0.4598, "high": 0.4604, "low": 0.4593, "open": 0.4593, "time": 1761498000, "volume": 2537}, {"close": 0.4607, "high": 0.461, "low": 0.4599, "open": 0.4607, "time": 1761494400, "volume": 6066}, {"close": 0.4618, "high": 0.4618, "low": 0.4587, "open": 0.459, "time": 1761490800, "volume": 176630}, {"close": 0.4605, "high": 0.4627, "low": 0.4598, "open": 0.4627, "time": 1761487200, "volume": 199380}, {"close": 0.4629, "high": 0.4634, "low": 0.459, "open": 0.4595, "time": 1761483600, "volume": 105338}, {"close": 0.46, "high": 0.4601, "low": 0.458, "open": 0.4589, "time": 1761480000, "volume": 14202}, {"close": 0.4583, "high": 0.4588, "low": 0.4508, "open": 0.4508, "time": 1761476400, "volume": 29568}, {"close": 0.4511, "high": 0.4538, "low": 0.4506, "open": 0.4538, "time": 1761472800, "volume": 27900}, {"close": 0.4536, "high": 0.4546, "low": 0.4483, "open": 0.4483, "time": 1761469200, "volume": 11464}, {"close": 0.4485, "high": 0.4485, "low": 0.4467, "open": 0.4467, "time": 1761465600, "volume": 134339}, {"close": 0.4457, "high": 0.4458, "low": 0.4443, "open": 0.4443, "time": 1761462000, "volume": 816}, {"close": 0.4445, "high": 0.4454, "low": 0.4437, "open": 0.4454, "time": 1761458400, "volume": 728}, {"close": 0.4451, "high": 0.4451, "low": 0.4429, "open": 0.4429, "time": 1761454800, "volume": 786}, {"close": 0.4427, "high": 0.4427, "low": 0.4408, "open": 0.4408, "time": 1761451200, "volume": 6310}, {"close": 0.4401, "high": 0.4416, "low": 0.4392, "open": 0.4408, "time": 1761447600, "volume": 157891}, {"close": 0.4409, "high": 0.4426, "low": 0.4401, "open": 0.4421, "time": 1761444000, "volume": 4590}, {"close": 0.4425, "high": 0.445, "low": 0.4425, "open": 0.4446, "time": 1761440400, "volume": 2061}, {"close": 0.446, "high": 0.446, "low": 0.4445, "open": 0.4445, "time": 1761436800, "volume": 1487}, {"close": 0.4483, "high": 0.4483, "low": 0.4483, "open": 0.4483, "time": 1761433200, "volume": 86}, {"close": 0.4478, "high": 0.4478, "low": 0.447, "open": 0.447, "time": 1761429600, "volume": 3952}, {"close": 0.4466, "high": 0.4485, "low": 0.4466, "open": 0.4485, "time": 1761426000, "volume": 201}, {"close": 0.4487, "high": 0.4501, "low": 0.4487, "open": 0.4501, "time": 1761422400, "volume": 3389}, {"close": 0.4493, "high": 0.4495, "low": 0.4492, "open": 0.4493, "time": 1761418800, "volume": 175066}, {"close": 0.4499, "high": 0.4505, "low": 0.446, "open": 0.446, "time": 1761415200, "volume": 345}, {"close": 0.447, "high": 0.447, "low": 0.4467, "open": 0.4469, "time": 1761411600, "volume": 1224}, {"close": 0.4461, "high": 0.4469, "low": 0.4451, "open": 0.4469, "time": 1761408000, "volume": 167991}, {"close": 0.4454, "high": 0.4462, "low": 0.4445, "open": 0.4445, "time": 1761404400, "volume": 10500}, {"close": 0.4457, "high": 0.446, "low": 0.444, "open": 0.444, "time": 1761400800, "volume": 8744}, {"close": 0.4443, "high": 0.4443, "low": 0.4435, "open": 0.4435, "time": 1761397200, "volume": 1423}, {"close": 0.4442, "high": 0.4446, "low": 0.4428, "open": 0.4428, "time": 1761393600, "volume": 6518}, {"close": 0.4431, "high": 0.4432, "low": 0.4408, "open": 0.4408, "time": 1761390000, "volume": 1221}, {"close": 0.4403, "high": 0.4403, "low": 0.4385, "open": 0.4385, "time": 1761386400, "volume": 1601}, {"close": 0.4411, "high": 0.4411, "low": 0.4408, "open": 0.4408, "time": 1761382800, "volume": 707}, {"close": 0.4406, "high": 0.4406, "low": 0.4395, "open": 0.4402, "time": 1761379200, "volume": 779}, {"close": 0.44, "high": 0.4432, "low": 0.4396, "open": 0.4409, "time": 1761375600, "volume": 32701}, {"close": 0.4403, "high": 0.4411, "low": 0.4403, "open": 0.441, "time": 1761372000, "volume": 1768}, {"close": 0.4413, "high": 0.4426, "low": 0.441, "open": 0.4426, "time": 1761368400, "volume": 45587}, {"close": 0.4124, "high": 0.4124, "low": 0.4111, "open": 0.4111, "time": 1762056000, "volume": 8450}, {"close": 0.4111, "high": 0.4124, "low": 0.4111, "open": 0.4123, "time": 1762052400, "volume": 376}, {"close": 0.4126, "high": 0.4126, "low": 0.4126, "open": 0.4126, "time": 1762048800, "volume": 0}, {"close": 0.4126, "high": 0.414, "low": 0.412, "open": 0.412, "time": 1762045200, "volume": 40350}, {"close": 0.4147, "high": 0.4147, "low": 0.4147, "open": 0.4147, "time": 1762041600, "volume": 4119}, {"close": 0.4147, "high": 0.4147, "low": 0.4147, "open": 0.4147, "time": 1762038000, "volume": 0}, {"close": 0.4147, "high": 0.4147, "low": 0.4147, "open": 0.4147, "time": 1762034400, "volume": 0}, {"close": 0.4147, "high": 0.4162, "low": 0.4147, "open": 0.4162, "time": 1762030800, "volume": 10406}, {"close": 0.4156, "high": 0.4161, "low": 0.4156, "open": 0.4156, "time": 1762027200, "volume": 8061}, {"close": 0.4131, "high": 0.4146, "low": 0.4127, "open": 0.414, "time": 1762023600, "volume": 7120}, {"close": 0.415, "high": 0.4151, "low": 0.4142, "open": 0.4142, "time": 1762020000, "volume": 2454}, {"close": 0.4145, "high": 0.415, "low": 0.412, "open": 0.412, "time": 1762016400, "volume": 22897}, {"close": 0.4134, "high": 0.4144, "low": 0.409, "open": 0.409, "time": 1762012800, "volume": 40328}, {"close": 0.4097, "high": 0.4097, "low": 0.4076, "open": 0.4076, "time": 1762009200, "volume": 8340}, {"close": 0.4074, "high": 0.408, "low": 0.4042, "open": 0.408, "time": 1762005600, "volume": 25395}, {"close": 0.4101, "high": 0.4133, "low": 0.4101, "open": 0.4131, "time": 1762002000, "volume": 3970}, {"close": 0.4099, "high": 0.4103, "low": 0.409, "open": 0.4101, "time": 1761998400, "volume": 4365}, {"close": 0.4081, "high": 0.4097, "low": 0.4081, "open": 0.4084, "time": 1761994800, "volume": 6916}, {"close": 0.4056, "high": 0.4062, "low": 0.4035, "open": 0.4047, "time": 1761991200, "volume": 31048}, {"close": 0.405, "high": 0.4082, "low": 0.405, "open": 0.4077, "time": 1761987600, "volume": 41218}, {"close": 0.4077, "high": 0.4077, "low": 0.404, "open": 0.4071, "time": 1761984000, "volume": 4624}, {"close": 0.4053, "high": 0.4062, "low": 0.3996, "open": 0.4001, "time": 1761980400, "volume": 8855}, {"close": 0.3993, "high": 0.3993, "low": 0.3972, "open": 0.3985, "time": 1761976800, "volume": 75727}, {"close": 0.3977, "high": 0.3996, "low": 0.3977, "open": 0.3985, "time": 1761973200, "volume": 2669}]